mysql_server/__init__.py
mysql_server/server.py
shubh_mcp_mysql_server-0.1.0.dist-info/METADATA
shubh_mcp_mysql_server-0.1.0.dist-info/WHEEL
shubh_mcp_mysql_server-0.1.0.dist-info/entry_points.txt
shubh_mcp_mysql_server-0.1.0.dist-info/RECORD
